datamanifest/__init__.py
datamanifest/manifest.py
datamanifest/data/manifest-ontology.ttl
datamanifest/data/manifest-shapes.ttl
datamanifest/data/manifest.ttl
datamanifest-0.1.1.dist-info/licenses/LICENSE
datamanifest-0.1.1.dist-info/METADATA
datamanifest-0.1.1.dist-info/WHEEL
datamanifest-0.1.1.dist-info/top_level.txt
datamanifest-0.1.1.dist-info/RECORD
