Metadata-Version: 2.4
Name: datamanifest
Version: 0.1.1
Summary: Support for Data Manifests
Author-email: Ora Lassila <ora@somanyaircraft.com>
License-Expression: BSD-3-Clause
Project-URL: Homepage, https://gitlab.com/somanyaircraft/datamanifest
Classifier: Development Status :: 4 - Beta
Classifier: Programming Language :: Python :: 3
Classifier: Operating System :: OS Independent
Requires-Python: >=3.10
License-File: LICENSE
Dynamic: license-file
